CHANGES
LICENSE
README.txt
bootstrap.py
buildout.cfg
setup.cfg
setup.py
iw/__init__.py
iw.mailhost.egg-info/PKG-INFO
iw.mailhost.egg-info/SOURCES.txt
iw.mailhost.egg-info/dependency_links.txt
iw.mailhost.egg-info/entry_points.txt
iw.mailhost.egg-info/namespace_packages.txt
iw.mailhost.egg-info/not-zip-safe
iw.mailhost.egg-info/requires.txt
iw.mailhost.egg-info/top_level.txt
iw/mailhost/README.txt
iw/mailhost/__init__.py
iw/mailhost/configure.zcml