Metadata-Version: 1.0
Name: iw.mailhost
Version: 0.3
Summary: Products.MailHost patch to use zope.sendmail
Home-page: UNKNOWN
Author: Ingeniweb
Author-email: support@ingeniweb.com
License: GPL
Keywords: plone smtp
Platform: UNKNOWN
Classifier: Programming Language :: Python
Classifier: Topic :: Software Development :: Libraries :: Python Modules
